fixar/__init__.py
fixar/fixar.py
fixar/test_fixar.py
fixar-1.0.0.dist-info/LICENSE.txt
fixar-1.0.0.dist-info/METADATA
fixar-1.0.0.dist-info/WHEEL
fixar-1.0.0.dist-info/top_level.txt
fixar-1.0.0.dist-info/RECORD
